bytegate/__init__.py
bytegate/_version.py
bytegate/client.py
bytegate/errors.py
bytegate/models.py
bytegate/py.typed
bytegate/router.py
bytegate/server.py
bytegate-0.1.1.dist-info/licenses/LICENSE
bytegate-0.1.1.dist-info/METADATA
bytegate-0.1.1.dist-info/WHEEL
bytegate-0.1.1.dist-info/top_level.txt
bytegate-0.1.1.dist-info/RECORD
